LICENSE
MANIFEST.in
README.md
copr-messaging.spec
requirements.txt
run_tests.sh
setup.py
copr_messaging/__init__.py
copr_messaging/fedora.py
copr_messaging/schema.py
copr_messaging/stomp.py
copr_messaging.egg-info/PKG-INFO
copr_messaging.egg-info/SOURCES.txt
copr_messaging.egg-info/dependency_links.txt
copr_messaging.egg-info/entry_points.txt
copr_messaging.egg-info/not-zip-safe
copr_messaging.egg-info/requires.txt
copr_messaging.egg-info/top_level.txt
copr_messaging/private/__init__.py
copr_messaging/private/consumer.py
copr_messaging/private/hierarchy.py
copr_messaging/private/schema_old.py
copr_messaging/private/schema_stomp_old.py
copr_messaging/tests/__init__.py
copr_messaging/tests/test_schema.py
docs/Makefile
docs/api.rst
docs/conf.py
docs/consuming.rst
docs/index.rst
docs/installation.rst