Metadata-Version: 2.1
Name: copr-messaging
Version: 1.2
Summary: A schema and tooling for Copr fedora-messaging
Home-page: https://github.com/fedora-copr/copr
Maintainer: Copr Team
Maintainer-email: copr-devel@lists.fedorahosted.org
License: GPLv2+
Keywords: fedora
Classifier: License :: OSI Approved :: GNU General Public License v2 or later (GPLv2+)
Classifier: Programming Language :: Python :: 3.7
License-File: LICENSE
Requires-Dist: copr-common
Requires-Dist: fedora-messaging
